CHANGES.txt
CONTRIBUTORS.txt
MANIFEST.in
README.txt
setup.cfg
setup.py
docs/HISTORY.txt
docs/INSTALL.txt
docs/LICENSE.GPL
docs/LICENSE.txt
my315ok/__init__.py
my315ok.watermarkImage.egg-info/PKG-INFO
my315ok.watermarkImage.egg-info/SOURCES.txt
my315ok.watermarkImage.egg-info/dependency_links.txt
my315ok.watermarkImage.egg-info/entry_points.txt
my315ok.watermarkImage.egg-info/namespace_packages.txt
my315ok.watermarkImage.egg-info/not-zip-safe
my315ok.watermarkImage.egg-info/paster_plugins.txt
my315ok.watermarkImage.egg-info/requires.txt
my315ok.watermarkImage.egg-info/top_level.txt
my315ok/watermarkImage/README.txt
my315ok/watermarkImage/__init__.py
my315ok/watermarkImage/config.py
my315ok/watermarkImage/configure.zcml
my315ok/watermarkImage/imgutl.py
my315ok/watermarkImage/logo.png
my315ok/watermarkImage/setuphandlers.py
my315ok/watermarkImage/watermarkfield.py
my315ok/watermarkImage/browser/__init__.py
my315ok/watermarkImage/browser/catalog_vocabulary.py
my315ok/watermarkImage/browser/configure.zcml
my315ok/watermarkImage/browser/controlpanel.py
my315ok/watermarkImage/browser/watermark.png
my315ok/watermarkImage/content/__init__.py
my315ok/watermarkImage/content/configure.zcml
my315ok/watermarkImage/content/watermark.py
my315ok/watermarkImage/content/watermarkimage.py
my315ok/watermarkImage/interfaces/__init__.py
my315ok/watermarkImage/interfaces/watermark.py
my315ok/watermarkImage/interfaces/watermarkimage.py
my315ok/watermarkImage/locales/my315ok.watermarkImage.pot
my315ok/watermarkImage/locales/zh/LC_MESSAGES/README.txt
my315ok/watermarkImage/locales/zh/LC_MESSAGES/my315ok.watermarkImage.mo
my315ok/watermarkImage/locales/zh/LC_MESSAGES/my315ok.watermarkImage.po
my315ok/watermarkImage/portlets/__init__.py
my315ok/watermarkImage/portlets/configure.zcml
my315ok/watermarkImage/profiles/default/actionicons.xml
my315ok/watermarkImage/profiles/default/browserlayer.xml
my315ok/watermarkImage/profiles/default/controlpanel.xml
my315ok/watermarkImage/profiles/default/factorytool.xml
my315ok/watermarkImage/profiles/default/metadata.xml
my315ok/watermarkImage/profiles/default/portlets.xml
my315ok/watermarkImage/profiles/default/propertiestool.xml
my315ok/watermarkImage/profiles/default/rolemap.xml
my315ok/watermarkImage/profiles/default/types.xml
my315ok/watermarkImage/profiles/default/types/WatermarkImage.xml
my315ok/watermarkImage/profiles/default/types/watermark.xml
