Metadata-Version: 1.0
Name: my315ok.watermarkImage
Version: 1.0
Summary: a image contenttype baseed ATImage that can attach a watermark logo
Home-page: http://svn.plone.org/svn/collective/
Author: adam tang
Author-email: yuejun.tang@gmail.com
License: GPL
Keywords: watermark plone
Platform: UNKNOWN
Classifier: Framework :: Plone
Classifier: Intended Audience :: Developers
Classifier: License :: OSI Approved :: GNU General Public License (GPL)
